dj_twenty_six_github_io-0.1.0.dist-info/METADATA
dj_twenty_six_github_io-0.1.0.dist-info/WHEEL
dj_twenty_six_github_io-0.1.0.dist-info/licenses/LICENSE.txt
dj_twenty_six_github_io-0.1.0.dist-info/licenses/LICENSE.txt:Zone.Identifier
dj_twenty_six_github_io/__init__.py
dj_twenty_six_github_io-0.1.0.dist-info/RECORD
