Metadata-Version: 2.1
Name: dj-twenty-six.github.io
Version: 0.1.0
Author-Email: qkrtnqls1216 <qkrtnqls991216@gmail.com>
License: MIT
Requires-Python: >=3.8
